{
  "Textures": [],
  "Models": [
    {
      "name": "sphere",
      "file": "sphere_hires.ply",
      "is_basic": true

    },
    {
      "name": "quad",
      "file": "flat.ply",
      "is_basic": true
    },
    {
      "name": "dalek",
      "file": "dalek.ply",
      "is_basic": true
    },
    {
      "name": "cube",
      "file": "cube.ply",
      "is_basic": true
    }
  ],
  "Animations": [],
  "Lights": [],
  "Entities": [
    {
      "name": "FreeCamera",
      "id": 1000,
      "components": [
        {
          "component": "position",
          "position": [ 0.0, 0.0, 0.0 ]
        },
        {
          "component": "camera",
          "active": true,
          "pitch": 0.0,
          "yaw": 0.0,
          "distance": 20.0
        }
      ]
    },
    {
      "name": "x",
      "components": [
        {
          "component": "position",
          "position": [ 0.0, 0.0, 0.0 ]
        },
        {
          "component": "rotation",
          "rotation": [ 0.0, 0.0, 0.0 ]
        },
        {
          "component": "velocity",
          "velocity": [ 0.0, 0.0, 0.0 ]
        },
        {
          "component": "render",
          "mesh": "dalek",
          "texture": "",
          "diffuse": [ 1.0, 0.8, 0.2, 1.0 ],
          "specular": [ 1.0, 1.0, 1.0, 0.9 ],
          "scale": [ 0.4, 0.4, 0.4 ],
          "ignore_lighting": false,
          "is_wireframe": false
        },
        {
          "component": "gatherer"
        }
      ]
    },
    {
      "name": "Object 2",
      "components": [
        {
          "component": "transform",
          "pos": [ 10.0, 100.0, 0.0 ],
          "rot": [ 0.0, 0.0, 0.0 ]
        },
        {
          "component": "light",
          "on": true,
          "diffuse": [ 1.0, 1.0, 1.0, 1.0 ],
          "specular": [ 1.0, 1.0, 1.0, 1.0 ],
          "const_atten": 0.0000001,
          "linear_atten": 0.012,
          "quad_atten": 0.000001,
          "direction": [ 0.0, -1.0, 0.0 ],
          "position": [ 0.0, 50.0, 0.0 ],
          "type": 0,
          "inner_angle": 5.0,
          "outer_angle": 10.0
        }
      ]
    }
  ]
}
